src/quadrature_oscillator_sync.v
//`timescale 1ns / 1ps

module quadrature_oscillator_sync(
    input clk,
    input load,                        // Preload signal
    input signed [7:0] re_coeff,
    input signed [7:0] im_coeff,
    input signed [7:0] power,
    input signed [7:0] accu_re_init,  // Initial real accumulator value
    input signed [7:0] accu_im_init,  // Initial imaginary accumulator value
    output reg signed [7:0] accu_re,  // Real part of accumulator
    output reg signed [7:0] accu_im   // Imaginary part of accumulator
);

    // Temporary variables for intermediate calculations
    reg signed [15:0] temp_re, temp_im;
    reg signed [7:0] tmph_re, tmph_im, t0;
    reg signed [15:0] ac3;

    // Always block for synchronous operation
    always @(posedge clk) begin
        if (load) begin
            // Load initial values into accumulators
            accu_re <= accu_re_init;
            accu_im <= accu_im_init;
        end else begin
            // Compute next values for real and imaginary parts
            temp_re = (accu_re * re_coeff) - (accu_im * im_coeff);
            temp_im = (accu_re * im_coeff) + (accu_im * re_coeff);

            // Scale down to fixed-point representation
            tmph_re = temp_re >>> 7;
            tmph_im = temp_im >>> 7;

            // Compute the power adjustment
            ac3 = (power <<< 8) - (tmph_re * tmph_re) - (tmph_im * tmph_im);
            t0 = ac3 >>> 8;

            // Apply power correction
            temp_re = temp_re + (tmph_re * t0);
            temp_im = temp_im + (tmph_im * t0);

            // Update the output accumulators
            accu_re <= temp_re >>> 7;
            accu_im <= temp_im >>> 7;
        end
    end

endmodule

test/quadrature_oscillator_sync_tb.v
`timescale 1ns / 1ps

module quadrature_oscillator_sync_tb;

    // Parameters
    reg clk;
    reg load;
    reg signed [7:0] re_coeff;
    reg signed [7:0] im_coeff;
    reg signed [7:0] power;
    reg signed [7:0] accu_re_init;
    reg signed [7:0] accu_im_init;
    wire signed [7:0] accu_re;
    wire signed [7:0] accu_im;

    // Number of iterations
    integer num_iterations = 1000;  // Specify the number of iterations here
    integer i;

    // Instantiate the quadrature oscillator module
    quadrature_oscillator_sync uut (
        .clk(clk),
        .load(load),
        .re_coeff(re_coeff),
        .im_coeff(im_coeff),
        .power(power),
        .accu_re_init(accu_re_init),
        .accu_im_init(accu_im_init),
        .accu_re(accu_re),
        .accu_im(accu_im)
    );

    // Clock generation
    initial begin
        clk = 0;
        forever #5 clk = ~clk;  // 10 time units clock period
    end

    // Test procedure
    initial begin
        $dumpfile("quadrature_oscillator_sync_tb.vcd");  // Specify the output VCD file
        $dumpvars(0, quadrature_oscillator_sync_tb);     // Dump all variables in the testbench
        // Initialize parameters
        re_coeff = 16'h7d;  // Example real coefficient
        im_coeff = 16'h1b;  // Example imaginary coefficient
        power = 16'h10;      // Target power level
        accu_re_init = 16'h20;  // Initial accumulator real part
        accu_im_init = 16'h0;    // Initial accumulator imaginary part

        // Preload the oscillator with initial values
        load = 1;
        #10; // Wait for 1 clock cycle to load initial values
        load = 0;

        // Run for the specified number of iterations
        for (i = 0; i < num_iterations; i = i + 1) begin
            #10;  // Wait for 1 clock cycle per iteration
            $display("%d, %d, %d", i, accu_re, accu_im);
        end

        // End simulation
        $finish;
    end

endmodule

sim/quadrature_oscillator_sync_tb.vcd
$date
	Sun Nov 10 16:29:17 2024
$end
$version
	Icarus Verilog
$end
$timescale
	1ps
$end
$scope module quadrature_oscillator_sync_tb $end
$var wire 8 ! accu_re [7:0] $end
$var wire 8 " accu_im [7:0] $end
$var reg 8 # accu_im_init [7:0] $end
$var reg 8 $ accu_re_init [7:0] $end
$var reg 1 % clk $end
$var reg 8 & im_coeff [7:0] $end
$var reg 1 ' load $end
$var reg 8 ( power [7:0] $end
$var reg 8 ) re_coeff [7:0] $end
$var integer 32 * i [31:0] $end
$var integer 32 + num_iterations [31:0] $end
$scope module uut $end
$var wire 8 , accu_im_init [7:0] $end
$var wire 8 - accu_re_init [7:0] $end
$var wire 1 % clk $end
$var wire 8 . im_coeff [7:0] $end
$var wire 1 ' load $end
$var wire 8 / power [7:0] $end
$var wire 8 0 re_coeff [7:0] $end
$var reg 16 1 ac3 [15:0] $end
$var reg 8 2 accu_im [7:0] $end
$var reg 8 3 accu_re [7:0] $end
$var reg 8 4 t0 [7:0] $end
$var reg 16 5 temp_im [15:0] $end
$var reg 16 6 temp_re [15:0] $end
$var reg 8 7 tmph_im [7:0] $end
$var reg 8 8 tmph_re [7:0] $end
$upscope $end
$upscope $end
$enddefinitions $end
#0
$dumpvars
bx 8
bx 7
bx 6
bx 5
bx 4
bx 3
bx 2
bx 1
b1111101 0
b10000 /
b11011 .
b100000 -
b0 ,
b1111101000 +
bx *
b1111101 )
b10000 (
1'
b11011 &
0%
b100000 $
b0 #
bx "
bx !
$end
#5000
b0 "
b0 2
b100000 !
b100000 3
1%
#10000
0%
b0 *
0'
#15000
b111 "
b111 2
b100010 !
b100010 3
b1100 4
b110000011011 1
b110 7
b11111 8
b1110101000 5
b1000100010100 6
1%
#20000
0%
b1 *
#25000
b1111 "
b1111 2
b1011 4
b101101111011 1
b1110 7
b11110011011 5
b1000100110010 6
1%
#30000
0%
b10 *
#35000
b10111 "
b10111 2
b100000 !
b100000 3
b1010 4
b101011000011 1
b10101 7
b11110 8
b101110111011 5
b1000000110001 6
1%
#40000
0%
b11 *
#45000
b11111 "
b11111 2
b11100 !
b11100 3
b101000010011 1
b11101 7
b11010 8
b111110111101 5
b111000110111 6
1%
#50000
0%
b100 *
#55000
b100110 "
b100110 2
b10110 !
b10110 3
b1001 4
b100101100000 1
b100100 7
b10100 8
b1001101011011 5
b101100011011 6
1%
#60000
0%
b101 *
#65000
b101100 "
b101100 2
b1110 !
b1110 3
b1000 4
b100011000110 1
b101001 7
b1101 8
b1011000101000 5
b11100100100 6
1%
#70000
0%
b110 *
#75000
b110000 "
b110000 2
b100 !
b100 3
b100000000111 1
b101101 7
b100 8
b1100001011110 5
b1001010010 6
1%
#80000
0%
b111 *
#85000
b110010 "
b110010 2
b11111001 !
b11111001 3
b111 4
b11100101110 1
b101111 7
b11111001 8
b1100100100101 5
b1111110010110011 6
1%
#90000
0%
b1000 *
#95000
b110001 "
b110001 2
b11101101 !
b11101101 3
b110 4
b11000011011 1
b11101110 8
b1100011000111 5
b1111011011100011 6
1%
#100000
0%
b1001 *
#105000
b101101 "
b101101 2
b11100001 !
b11100001 3
b101 4
b10101111110 1
b101011 7
b11100011 8
b1011011000011 5
b1111000011111101 6
1%
#110000
0%
b1010 *
#115000
b100110 "
b100110 2
b11010110 !
b11010110 3
b100 4
b10001100111 1
b100101 7
b11011000 8
b1001101001000 5
b1110101101111110 6
1%
#120000
0%
b1011 *
#125000
b11100 "
b11100 2
b11001101 !
b11001101 3
b11 4
b1100101100 1
b11100 7
b11001110 8
b111001110100 5
b1110011011100110 6
1%
#130000
0%
b1100 *
#135000
b10000 "
b10000 2
b11000111 !
b11000111 3
b10 4
b1011000000 1
b10000 7
b11001000 8
b100001101011 5
b1110001110110101 6
1%
#140000
0%
b1101 *
#145000
b11 "
b11 2
b11000100 !
b11000100 3
b1 4
b111100111 1
b11 7
b11000100 8
b111010000 5
b1110001000111111 6
1%
#150000
0%
b1110 *
#155000
b11110110 "
b11110110 2
b110001100 1
b11110110 7
b1111101100011001 5
b1110001000100111 6
1%
#160000
0%
b1111 *
#165000
b11101001 "
b11101001 2
b11000111 !
b11000111 3
b100111110 1
b11101001 7
b11000111 8
b1111010010110011 5
b1110001110001001 6
1%
#170000
0%
b10000 *
#175000
b11011101 "
b11011101 2
b11001100 !
b11001100 3
b100001110 1
b11011101 7
b11001101 8
b1110111010011111 5
b1110011001100101 6
1%
#180000
0%
b10001 *
#185000
b11010010 "
b11010010 2
b11010100 !
b11010100 3
b0 4
b101100 1
b11010010 7
b11010100 8
b1110100101101101 5
b1110101001001101 6
1%
#190000
0%
b10010 *
#195000
b11001010 "
b11001010 2
b11011111 !
b11011111 3
b11111111 4
b1111111110101011 1
b11001001 7
b11011110 8
b1110010100011101 5
b1110111110000000 6
1%
#200000
0%
b10011 *
#205000
b11000100 "
b11000100 2
b11101011 !
b11101011 3
b0 4
b110111 1
b11000100 7
b11101011 8
b1110001000100111 5
b1111010110010101 6
1%
#210000
0%
b10100 *
#215000
b11000001 "
b11000001 2
b11111000 !
b11111000 3
b11111111 4
b1111111111000000 1
b11000000 7
b11111000 8
b1110000010111101 5
b1111110000011011 6
1%
#220000
0%
b10101 *
#225000
b101 !
b101 3
b1111111111100111 1
b101 8
b1110000010100101 5
b1010111000 6
1%
#230000
0%
b10110 *
#235000
b11000011 "
b11000011 2
b10010 !
b10010 3
b0 4
b110011 1
b11000011 7
b10010 8
b1110000111000100 5
b100100010110 6
1%
#240000
0%
b10111 *
#245000
b11001000 "
b11001000 2
b11110 !
b11110 3
b111100 1
b11001000 7
b11110 8
b1110010000011101 5
b111100111001 6
1%
#250000
0%
b11000 *
#255000
b11001111 "
b11001111 2
b101001 !
b101001 3
b1110 1
b11001111 7
b101001 8
b1110011111010010 5
b1010010001110 6
1%
#260000
0%
b11001 *
#265000
b11011001 "
b11011001 2
b110001 !
b110001 3
b11111111 4
b1111111111111100 1
b11011000 7
b110010 8
b1110110010001110 5
b1100011111110 6
1%
#270000
0%
b11010 *
#275000
b11100100 "
b11100100 2
b111000 !
b111000 3
b0 4
b10110000 1
b11100100 7
b111000 8
b1111001000100000 5
b1110000001010 6
1%
#280000
0%
b11011 *
#285000
b11110000 "
b11110000 2
b111100 !
b111100 3
b11110000 1
b11110000 7
b111100 8
b1111100000111100 5
b1111001001100 6
1%
#290000
0%
b11100 *
#295000
b11111101 "
b11111101 2
b111110 !
b111110 3
b1 4
b101101110 1
b11111101 7
b111101 8
b1111111010000001 5
b1111100111001 6
1%
#300000
0%
b11101 *
#305000
b1010 "
b1010 2
b111101 !
b111101 3
b100010011 1
b1010 7
b10100011101 5
b1111011010100 6
1%
#310000
0%
b11110 *
#315000
b10110 "
b10110 2
b111001 !
b111001 3
b101101011 1
b10110 7
b111001 8
b101101100111 5
b1110011110100 6
1%
#320000
0%
b11111 *
#325000
b100001 "
b100001 2
b110011 !
b110011 3
b110010110 1
b100001 7
b110011 8
b1000011100010 5
b1100110110110 6
1%
#330000
0%
b100000 *
#335000
b101011 "
b101011 2
b101011 !
b101011 3
b10 4
b1000111000 1
b101010 7
b101010 8
b1010111010010 5
b1010111000000 6
1%
#340000
0%
b100001 *
#345000
b110011 "
b110011 2
b100001 !
b100001 3
b1 4
b111010111 1
b110011 7
b100000 8
b1100110111011 5
b1000010010110 6
1%
#350000
0%
b100010 *
#355000
b111001 "
b111001 2
b10101 !
b10101 3
b10 4
b1000000111 1
b111000 7
b10101 8
b1110011010010 5
b101011100110 6
1%
#360000
0%
b100011 *
#365000
b111100 "
b111100 2
b1000 !
b1000 3
b1 4
b110110000 1
b111100 7
b1000 8
b1111001001000 5
b10001000110 6
1%
#370000
0%
b100100 *
#375000
b11111011 !
b11111011 3
b111010111 1
b11111011 8
b1111001100000 5
b1111110110001111 6
1%
#380000
0%
b100101 *
#385000
b111010 "
b111010 2
b11101110 !
b11101110 3
b10 4
b1000001011 1
b111001 7
b11101110 8
b1110100110111 5
b1111011100010111 6
1%
#390000
0%
b100110 *
#395000
b110101 "
b110101 2
b11100001 !
b11100001 3
b1 4
b111101100 1
b110100 7
b11100010 8
b1101010100000 5
b1111000011111010 6
1%
#400000
0%
b100111 *
#405000
b101101 "
b101101 2
b11010110 !
b11010110 3
b100110011 1
b101101 7
b11010110 8
b1011011001001 5
b1110101100011100 6
1%
#410000
0%
b101000 *
#415000
b100011 "
b100011 2
b11001101 !
b11001101 3
b100001110 1
b100011 7
b11001101 8
b1000110101110 5
b1110011010001100 6
1%
#420000
0%
b101001 *
#425000
b10111 "
b10111 2
b11000110 !
b11000110 3
b0 4
b11001011 1
b10111 7
b11000110 8
b101110110110 5
b1110001101101000 6
1%
#430000
0%
b101010 *
#435000
b1010 "
b1010 2
b11000010 !
b11000010 3
b10011000 1
b1010 7
b11000010 8
b10100011101 5
b1110000101000001 6
1%
#440000
0%
b101011 *
#445000
b11111100 "
b11111100 2
b11000001 !
b11000001 3
b1101111 1
b11111100 7
b11000001 8
b1111111001011000 5
b1110000010101100 6
1%
#450000
0%
b101100 *
#455000
b11101110 "
b11101110 2
b11000011 !
b11000011 3
b110011 1
b11101110 7
b11000011 8
b1111011101100111 5
b1110000110101001 6
1%
#460000
0%
b101101 *
#465000
b11100001 "
b11100001 2
b11001000 !
b11001000 3
b11111111 4
b1111111111111111 1
b11100001 7
b11001000 8
b1111000011100110 5
b1110010001010101 6
1%
#470000
0%
b101110 *
#475000
b11010110 "
b11010110 2
b11010000 !
b11010000 3
b1111111101100110 1
b11010101 7
b11001111 8
b1110101100100000 5
b1110100000011110 6
1%
#480000
0%
b101111 *
#485000
b11001101 "
b11001101 2
b11011010 !
b11011010 3
b1111111101111111 1
b11001100 7
b11011001 8
b1110011010100010 5
b1110110100100101 6
1%
#490000
0%
b110000 *
#495000
b11000110 "
b11000110 2
b11100101 !
b11100101 3
b0 4
b11 1
b11000110 7
b11100101 8
b1110001100010111 5
b1111001011010011 6
1%
#500000
0%
b110001 *
#505000
b11000010 "
b11000010 2
b11110001 !
b11110001 3
b11111111 4
b1111111110011110 1
b11000001 7
b11110001 8
b1110000100010100 5
b1111100011111110 6
1%
#510000
0%
b110010 *
#515000
b11000000 "
b11000000 2
b11111110 !
b11111110 3
b1111111111111100 1
b11000000 7
b11111110 8
b1110000001100101 5
b1111111100111001 6
1%
#520000
0%
b110011 *
#525000
b11000001 "
b11000001 2
b1011 !
b1011 3
b0 4
b110 1
b11000001 7
b1011 8
b1110000010001010 5
b10111000110 6
1%
#530000
0%
b110100 *
#535000
b11000101 "
b11000101 2
b10111 !
b10111 3
b11111111 4
b1111111110110000 1
b11000100 7
b11000 8
b1110001010100010 5
b101111101100 6
1%
#540000
0%
b110101 *
#545000
b11001011 "
b11001011 2
b100010 !
b100010 3
b0 4
b10000011 1
b11001011 7
b100010 8
b1110010110011110 5
b1000101110100 6
1%
#550000
0%
b110110 *
#555000
b11010011 "
b11010011 2
b101100 !
b101100 3
b10000111 1
b11010011 7
b101100 8
b1110100110110101 5
b1011000110001 6
1%
#560000
0%
b110111 *
#565000
b11011101 "
b11011101 2
b110100 !
b110100 3
b10100111 1
b11011101 7
b110100 8
b1110111010101011 5
b1101000111011 6
1%
#570000
0%
b111000 *
#575000
b11101000 "
b11101000 2
b111010 !
b111010 3
b10011100 1
b11101000 7
b111010 8
b1111010001100101 5
b1110100010101 6
1%
#580000
0%
b111001 *
#585000
b11110100 "
b11110100 2
b111101 !
b111101 3
b11100111 1
b11110100 7
b111101 8
b1111101001100110 5
b1111011011010 6
1%
#590000
0%
b111010 *
#595000
b1 "
b1 2
b111110 !
b111110 3
b11111011 1
b1 7
b111110 8
b10010011 5
b1111100001101 6
1%
#600000
0%
b111011 *
#605000
b1110 "
b1110 2
b111100 !
b111100 3
b1 4
b100101100 1
b1110 7
b111100 8
b11100010101 5
b1111001100111 6
1%
#610000
0%
b111100 *
#615000
b11010 "
b11010 2
b111000 !
b111000 3
b110001011 1
b11010 7
b110111 8
b110101000100 5
b1110000001001 6
1%
#620000
0%
b111101 *
#625000
b100101 "
b100101 2
b110001 !
b110001 3
b101000110 1
b100101 7
b110001 8
b1001010111111 5
b1100011001011 6
1%
#630000
0%
b111110 *
#635000
b101110 "
b101110 2
b101000 !
b101000 3
b101111100 1
b101110 7
b101000 8
b1011101101010 5
b1010000101110 6
1%
#640000
0%
b111111 *
#645000
b110101 "
b110101 2
b11101 !
b11101 3
b110111110 1
b110101 7
b11101 8
b1101011100011 5
b111011001011 6
1%
#650000
0%
b1000000 *
#655000
b111010 "
b111010 2
b10001 !
b10001 3
b10 4
b1000101110 1
b111001 7
b10001 8
b1110101100010 5
b100010110100 6
1%
#660000
0%
b1000001 *
#665000
b111100 "
b111100 2
b100 !
b100 3
b1 4
b111100000 1
b111100 7
b100 8
b1111001011001 5
b1000110011 6
1%
#670000
0%
b1000010 *
#675000
b11110111 !
b11110111 3
b10 4
b1000010110 1
b111011 7
b11110111 8
b1111000101110 5
b1111101110001110 6
1%
#680000
0%
b1000011 *
#685000
b111001 "
b111001 2
b11101010 !
b11101010 3
b1 4
b111011100 1
b111000 7
b11101010 8
b1110010010001 5
b1111010100110001 6
1%
#690000
0%
b1000100 *
#695000
b110011 "
b110011 2
b11011110 !
b11011110 3
b101010011 1
b110011 7
b11011110 8
b1100110110110 5
b1110111100011101 6
1%
#700000
0%
b1000101 *
#705000
b101010 "
b101010 2
b11010011 !
b11010011 3
b110001100 1
b101010 7
b11010100 8
b1010101111011 5
b1110100111011001 6
1%
#710000
0%
b1000110 *
#715000
b11111 "
b11111 2
b11001010 !
b11001010 3
b101000110 1
b11111 7
b11001011 8
b111111100010 5
b1110010101100100 6
1%
#720000
0%
b1000111 *
#725000
b10010 "
b10010 2
b11000100 !
b11000100 3
b0 4
b10101100 1
b10010 7
b11000100 8
b100101110001 5
b1110001001011101 6
1%
#730000
0%
b1001000 *
#735000
b100 "
b100 2
b11000001 !
b11000001 3
b1101111 1
b100 7
b11000001 8
b1001110110 5
b1110000011001110 6
1%
#740000
0%
b1001001 *
#745000
b11110110 "
b11110110 2
b11011 1
b11110110 7
b1111101101001111 5
b1110000011010001 6
1%
#750000
0%
b1001010 *
#755000
b11101001 "
b11101001 2
b11000101 !
b11000101 3
b11111111 4
b1111111110110000 1
b11101000 7
b11000100 8
b1111010010010001 5
b1110001010000111 6
1%
#760000
0%
b1001011 *
#765000
b11011101 "
b11011101 2
b11001011 !
b11001011 3
b0 4
b111110 1
b11011101 7
b11001011 8
b1110111010001100 5
b1110010110011110 6
1%
#770000
0%
b1001100 *
#775000
b11010011 "
b11010011 2
b11010011 !
b11010011 3
b11111111 4
b1111111111010011 1
b11010010 7
b11010011 8
b1110100110000000 5
b1110100111111101 6
1%
#780000
0%
b1001101 *
#785000
b11001010 "
b11001010 2
b11011101 !
b11011101 3
b11001010 7
b11011101 8
b1110010101111110 5
b1110111011101001 6
1%
#790000
0%
b1001110 *
#795000
b11000100 "
b11000100 2
b11101001 !
b11101001 3
b1111111101100110 1
b11000011 7
b11101001 8
b1110001000101110 5
b1111010010110010 6
1%
#800000
0%
b1001111 *
#805000
b11000001 "
b11000001 2
b11110110 !
b11110110 3
b1111111110011100 1
b11000000 7
b11110110 8
b1110000010000111 5
b1111101100100011 6
1%
#810000
0%
b1010000 *
#815000
b11000000 "
b11000000 2
b11 !
b11 3
b1111111111110111 1
b11 8
b1110000001101111 5
b111000000 6
1%
#820000
0%
b1010001 *
#825000
b11000010 "
b11000010 2
b10000 !
b10000 3
b1111111111111100 1
b11000010 7
b10000 8
b1110000101001111 5
b100000100111 6
1%
#830000
0%
b1010010 *
#835000
b11000111 "
b11000111 2
b11100 !
b11100 3
b1111111111001100 1
b11000110 7
b11100 8
b1110001110100100 5
b111000111110 6
1%
#840000
0%
b1010011 *
#845000
b11001110 "
b11001110 2
b100111 !
b100111 3
b0 4
b1001011 1
b11001110 7
b100111 8
b1110011100011111 5
b1001110101111 6
1%
#850000
0%
b1010100 *
#855000
b11010111 "
b11010111 2
b110000 !
b110000 3
b1101111 1
b11010111 7
b110000 8
b1110101110110011 5
b1100001010001 6
1%
#860000
0%
b1010101 *
#865000
b11100010 "
b11100010 2
b110111 !
b110111 3
b10101011 1
b11100010 7
b110111 8
b1111000100001011 5
b1101111000011 6
1%
#870000
0%
b1010110 *
#875000
b11101110 "
b11101110 2
b111100 !
b111100 3
b10101100 1
b11101110 7
b111100 8
b1111011100100111 5
b1111000000101 6
1%
#880000
0%
b1010111 *
#885000
b11111011 "
b11111011 2
b111110 !
b111110 3
b11100011 1
b11111011 7
b111110 8
b1111110110001010 5
b1111100110010 6
1%
#890000
0%
b1011000 *
#895000
b1000 "
b1000 2
b1 4
b100110111 1
b1000 7
b111101 8
b10000100001 5
b1111100001010 6
1%
#900000
0%
b1011001 *
#905000
b10101 "
b10101 2
b111011 !
b111011 3
b101001100 1
b10100 7
b111010 8
b101010000110 5
b1110110101000 6
1%
#910000
0%
b1011010 *
#915000
b100001 "
b100001 2
b110101 !
b110101 3
b100000111 1
b100000 7
b110101 8
b1000010011010 5
b1101011001101 6
1%
#920000
0%
b1011011 *
#925000
b101011 "
b101011 2
b101101 !
b101101 3
b100110111 1
b101011 7
b101100 8
b1010111011111 5
b1011010010010 6
1%
#930000
0%
b1011100 *
#935000
b110011 "
b110011 2
b100011 !
b100011 3
b101010011 1
b110011 7
b100010 8
b1100111110001 5
b1000110010010 6
1%
#940000
0%
b1011101 *
#945000
b111001 "
b111001 2
b10111 !
b10111 3
b100111110 1
b111001 7
b10111 8
b1110011010001 5
b101111001101 6
1%
#950000
0%
b1011110 *
#955000
b111100 "
b111100 2
b1010 !
b1010 3
b110001100 1
b111100 7
b1010 8
b1111001111110 5
b10101000010 6
1%
#960000
0%
b1011111 *
#965000
b111101 "
b111101 2
b11111101 !
b11111101 3
b111100111 1
b11111101 8
b1111010010110 5
b1111111010001011 6
1%
#970000
0%
b1100000 *
#975000
b111011 "
b111011 2
b11110000 !
b11110000 3
b111011100 1
b111010 7
b11110000 8
b1110110110010 5
b1111100000001010 6
1%
#980000
0%
b1100001 *
#985000
b110110 "
b110110 2
b11100011 !
b11100011 3
b101010011 1
b110110 7
b11100011 8
b1101101010101 5
b1111000111011010 6
1%
#990000
0%
b1100010 *
#995000
b101110 "
b101110 2
b11010111 !
b11010111 3
b101111100 1
b101110 7
b11011000 8
b1011101111101 5
b1110101111111101 6
1%
#1000000
0%
b1100011 *
#1005000
b100100 "
b100100 2
b11001101 !
b11001101 3
b100101100 1
b100100 7
b11001110 8
b1001001000111 5
b1110011011101111 6
1%
#1010000
0%
b1100100 *
#1015000
b11000 "
b11000 2
b11000110 !
b11000110 3
b0 4
b10011100 1
b11000 7
b11000110 8
b110000110011 5
b1110001101001101 6
1%
#1020000
0%
b1100101 *
#1025000
b1011 "
b1011 2
b11000010 !
b11000010 3
b10000011 1
b1011 7
b11000010 8
b10110011010 5
b1110000100100110 6
1%
#1030000
0%
b1100110 *
#1035000
b11111101 "
b11111101 2
b11000001 !
b11000001 3
b1110110 1
b11111101 7
b11000001 8
b1111111011010101 5
b1110000010010001 6
1%
#1040000
0%
b1100111 *
#1045000
b11101111 "
b11101111 2
b11000011 !
b11000011 3
b1010110 1
b11101111 7
b11000011 8
b1111011111100100 5
b1110000110001110 6
1%
#1050000
0%
b1101000 *
#1055000
b11100010 "
b11100010 2
b11001000 !
b11001000 3
b111100 1
b11100010 7
b11001000 8
b1111000101000100 5
b1110010000000010 6
1%
#1060000
0%
b1101001 *
#1065000
b11010111 "
b11010111 2
b11010000 !
b11010000 3
b11111111 4
b1111111110111011 1
b11010110 7
b11001111 8
b1110101110011100 5
b1110100000000011 6
1%
#1070000
0%
b1101010 *
#1075000
b11001110 "
b11001110 2
b11011010 !
b11011010 3
b1111111111100110 1
b11001101 7
b11011001 8
b1110011100011110 5
b1110110100001010 6
1%
#1080000
0%
b1101011 *
#1085000
b11000111 "
b11000111 2
b11100101 !
b11100101 3
b0 4
b1110110 1
b11000111 7
b11100101 8
b1110001110010100 5
b1111001010111000 6
1%
#1090000
0%
b1101100 *
#1095000
b11000010 "
b11000010 2
b11110001 !
b11110001 3
b11011 1
b11000010 7
b11110001 8
b1110000101010010 5
b1111100011010100 6
1%
#1100000
0%
b1101101 *
#1105000
b11000000 "
b11000000 2
b11111110 !
b11111110 3
b11111111 4
b1111111111111100 1
b11000000 7
b11111110 8
b1110000001100101 5
b1111111100111001 6
1%
#1110000
0%
b1101110 *
#1115000
b11000001 "
b11000001 2
b1011 !
b1011 3
b0 4
b110 1
b11000001 7
b1011 8
b1110000010001010 5
b10111000110 6
1%
#1120000
0%
b1101111 *
#1125000
b11000101 "
b11000101 2
b10111 !
b10111 3
b11111111 4
b1111111110110000 1
b11000100 7
b11000 8
b1110001010100010 5
b101111101100 6
1%
#1130000
0%
b1110000 *
#1135000
b11001011 "
b11001011 2
b100010 !
b100010 3
b0 4
b10000011 1
b11001011 7
b100010 8
b1110010110011110 5
b1000101110100 6
1%
#1140000
0%
b1110001 *
#1145000
b11010011 "
b11010011 2
b101100 !
b101100 3
b10000111 1
b11010011 7
b101100 8
b1110100110110101 5
b1011000110001 6
1%
#1150000
0%
b1110010 *
#1155000
b11011101 "
b11011101 2
b110100 !
b110100 3
b10100111 1
b11011101 7
b110100 8
b1110111010101011 5
b1101000111011 6
1%
#1160000
0%
b1110011 *
#1165000
b11101000 "
b11101000 2
b111010 !
b111010 3
b10011100 1
b11101000 7
b111010 8
b1111010001100101 5
b1110100010101 6
1%
#1170000
0%
b1110100 *
#1175000
b11110100 "
b11110100 2
b111101 !
b111101 3
b11100111 1
b11110100 7
b111101 8
b1111101001100110 5
b1111011011010 6
1%
#1180000
0%
b1110101 *
#1185000
b1 "
b1 2
b111110 !
b111110 3
b11111011 1
b1 7
b111110 8
b10010011 5
b1111100001101 6
1%
#1190000
0%
b1110110 *
#1195000
b1110 "
b1110 2
b111100 !
b111100 3
b1 4
b100101100 1
b1110 7
b111100 8
b11100010101 5
b1111001100111 6
1%
#1200000
0%
b1110111 *
#1205000
b11010 "
b11010 2
b111000 !
b111000 3
b110001011 1
b11010 7
b110111 8
b110101000100 5
b1110000001001 6
1%
#1210000
0%
b1111000 *
#1215000
b100101 "
b100101 2
b110001 !
b110001 3
b101000110 1
b100101 7
b110001 8
b1001010111111 5
b1100011001011 6
1%
#1220000
0%
b1111001 *
#1225000
b101110 "
b101110 2
b101000 !
b101000 3
b101111100 1
b101110 7
b101000 8
b1011101101010 5
b1010000101110 6
1%
#1230000
0%
b1111010 *
#1235000
b110101 "
b110101 2
b11101 !
b11101 3
b110111110 1
b110101 7
b11101 8
b1101011100011 5
b111011001011 6
1%
#1240000
0%
b1111011 *
#1245000
b111010 "
b111010 2
b10001 !
b10001 3
b10 4
b1000101110 1
b111001 7
b10001 8
b1110101100010 5
b100010110100 6
1%
#1250000
0%
b1111100 *
#1255000
b111100 "
b111100 2
b100 !
b100 3
b1 4
b111100000 1
b111100 7
b100 8
b1111001011001 5
b1000110011 6
1%
#1260000
0%
b1111101 *
#1265000
b11110111 !
b11110111 3
b10 4
b1000010110 1
b111011 7
b11110111 8
b1111000101110 5
b1111101110001110 6
1%
#1270000
0%
b1111110 *
#1275000
b111001 "
b111001 2
b11101010 !
b11101010 3
b1 4
b111011100 1
b111000 7
b11101010 8
b1110010010001 5
b1111010100110001 6
1%
#1280000
0%
b1111111 *
#1285000
b110011 "
b110011 2
b11011110 !
b11011110 3
b101010011 1
b110011 7
b11011110 8
b1100110110110 5
b1110111100011101 6
1%
#1290000
0%
b10000000 *
#1295000
b101010 "
b101010 2
b11010011 !
b11010011 3
b110001100 1
b101010 7
b11010100 8
b1010101111011 5
b1110100111011001 6
1%
#1300000
0%
b10000001 *
#1305000
b11111 "
b11111 2
b11001010 !
b11001010 3
b101000110 1
b11111 7
b11001011 8
b111111100010 5
b1110010101100100 6
1%
#1310000
0%
b10000010 *
#1315000
b10010 "
b10010 2
b11000100 !
b11000100 3
b0 4
b10101100 1
b10010 7
b11000100 8
b100101110001 5
b1110001001011101 6
1%
#1320000
0%
b10000011 *
#1325000
b100 "
b100 2
b11000001 !
b11000001 3
b1101111 1
b100 7
b11000001 8
b1001110110 5
b1110000011001110 6
1%
#1330000
0%
b10000100 *
#1335000
b11110110 "
b11110110 2
b11011 1
b11110110 7
b1111101101001111 5
b1110000011010001 6
1%
#1340000
0%
b10000101 *
#1345000
b11101001 "
b11101001 2
b11000101 !
b11000101 3
b11111111 4
b1111111110110000 1
b11101000 7
b11000100 8
b1111010010010001 5
b1110001010000111 6
1%
#1350000
0%
b10000110 *
#1355000
b11011101 "
b11011101 2
b11001011 !
b11001011 3
b0 4
b111110 1
b11011101 7
b11001011 8
b1110111010001100 5
b1110010110011110 6
1%
#1360000
0%
b10000111 *
#1365000
b11010011 "
b11010011 2
b11010011 !
b11010011 3
b11111111 4
b1111111111010011 1
b11010010 7
b11010011 8
b1110100110000000 5
b1110100111111101 6
1%
#1370000
0%
b10001000 *
#1375000
b11001010 "
b11001010 2
b11011101 !
b11011101 3
b11001010 7
b11011101 8
b1110010101111110 5
b1110111011101001 6
1%
#1380000
0%
b10001001 *
#1385000
b11000100 "
b11000100 2
b11101001 !
b11101001 3
b1111111101100110 1
b11000011 7
b11101001 8
b1110001000101110 5
b1111010010110010 6
1%
#1390000
0%
b10001010 *
#1395000
b11000001 "
b11000001 2
b11110110 !
b11110110 3
b1111111110011100 1
b11000000 7
b11110110 8
b1110000010000111 5
b1111101100100011 6
1%
#1400000
0%
b10001011 *
#1405000
b11000000 "
b11000000 2
b11 !
b11 3
b1111111111110111 1
b11 8
b1110000001101111 5
b111000000 6
1%
#1410000
0%
b10001100 *
#1415000
b11000010 "
b11000010 2
b10000 !
b10000 3
b1111111111111100 1
b11000010 7
b10000 8
b1110000101001111 5
b100000100111 6
1%
#1420000
0%
b10001101 *
#1425000
b11000111 "
b11000111 2
b11100 !
b11100 3
b1111111111001100 1
b11000110 7
b11100 8
b1110001110100100 5
b111000111110 6
1%
#1430000
0%
b10001110 *
#1435000
b11001110 "
b11001110 2
b100111 !
b100111 3
b0 4
b1001011 1
b11001110 7
b100111 8
b1110011100011111 5
b1001110101111 6
1%
#1440000
0%
b10001111 *
#1445000
b11010111 "
b11010111 2
b110000 !
b110000 3
b1101111 1
b11010111 7
b110000 8
b1110101110110011 5
b1100001010001 6
1%
#1450000
0%
b10010000 *
#1455000
b11100010 "
b11100010 2
b110111 !
b110111 3
b10101011 1
b11100010 7
b110111 8
b1111000100001011 5
b1101111000011 6
1%
#1460000
0%
b10010001 *
