src/quadrature_oscillator_sync.v
//`timescale 1ns / 1ps

module quadrature_oscillator_sync(
    input clk,
    input load,                        // Preload signal
    input signed [15:0] re_coeff,
    input signed [15:0] im_coeff,
    input signed [15:0] power,
    input signed [15:0] accu_re_init,  // Initial real accumulator value
    input signed [15:0] accu_im_init,  // Initial imaginary accumulator value
    output reg signed [15:0] accu_re,  // Real part of accumulator
    output reg signed [15:0] accu_im   // Imaginary part of accumulator
);

    // Temporary variables for intermediate calculations
    reg signed [31:0] temp_re, temp_im;
    reg signed [15:0] tmph_re, tmph_im, t0;
    reg signed [31:0] ac3;

    // Always block for synchronous operation
    always @(posedge clk) begin
        if (load) begin
            // Load initial values into accumulators
            accu_re <= accu_re_init;
            accu_im <= accu_im_init;
        end else begin
            // Compute next values for real and imaginary parts
            temp_re = (accu_re * re_coeff) - (accu_im * im_coeff);
            temp_im = (accu_re * im_coeff) + (accu_im * re_coeff);

            // Scale down to fixed-point representation
            tmph_re = temp_re >>> 15;
            tmph_im = temp_im >>> 15;

            // Compute the power adjustment
            ac3 = (power <<< 16) - (tmph_re * tmph_re) - (tmph_im * tmph_im);
            t0 = ac3 >>> 16;

            // Apply power correction
            temp_re = temp_re + (tmph_re * t0);
            temp_im = temp_im + (tmph_im * t0);

            // Update the output accumulators
            accu_re <= temp_re >>> 15;
            accu_im <= temp_im >>> 15;
        end
    end

endmodule

test/quadrature_oscillator_sync_tb.v
`timescale 1ns / 1ps

module quadrature_oscillator_sync_tb;

    // Parameters
    reg clk;
    reg load;
    reg signed [15:0] re_coeff;
    reg signed [15:0] im_coeff;
    reg signed [15:0] power;
    reg signed [15:0] accu_re_init;
    reg signed [15:0] accu_im_init;
    wire signed [15:0] accu_re;
    wire signed [15:0] accu_im;

    // Number of iterations
    integer num_iterations = 1000;  // Specify the number of iterations here
    integer i;

    // Instantiate the quadrature oscillator module
    quadrature_oscillator_sync uut (
        .clk(clk),
        .load(load),
        .re_coeff(re_coeff),
        .im_coeff(im_coeff),
        .power(power),
        .accu_re_init(accu_re_init),
        .accu_im_init(accu_im_init),
        .accu_re(accu_re),
        .accu_im(accu_im)
    );

    // Clock generation
    initial begin
        clk = 0;
        forever #5 clk = ~clk;  // 10 time units clock period
    end

    // Test procedure
    initial begin
        $dumpfile("quadrature_oscillator_sync_tb.vcd");  // Specify the output VCD file
        $dumpvars(0, quadrature_oscillator_sync_tb);     // Dump all variables in the testbench
        // Initialize parameters
        re_coeff = 16'h7d34;  // Example real coefficient
        im_coeff = 16'h1a9d;  // Example imaginary coefficient
        power = 16'h400;      // Target power level
        accu_re_init = 16'h20;  // Initial accumulator real part
        accu_im_init = 16'h0;    // Initial accumulator imaginary part

        // Preload the oscillator with initial values
        load = 1;
        #10; // Wait for 1 clock cycle to load initial values
        load = 0;

        // Run for the specified number of iterations
        for (i = 0; i < num_iterations; i = i + 1) begin
            #10;  // Wait for 1 clock cycle per iteration
            $display("%d, %d, %d", i, accu_re, accu_im);
        end

        // End simulation
        $finish;
    end

endmodule

sim/quadrature_oscillator_sync_tb.vcd
$date
	Sun Nov 10 11:27:13 2024
$end
$version
	Icarus Verilog
$end
$timescale
	1ps
$end
$scope module quadrature_oscillator_sync_tb $end
$var wire 16 ! accu_re [15:0] $end
$var wire 16 " accu_im [15:0] $end
$var reg 16 # accu_im_init [15:0] $end
$var reg 16 $ accu_re_init [15:0] $end
$var reg 1 % clk $end
$var reg 16 & im_coeff [15:0] $end
$var reg 1 ' load $end
$var reg 16 ( power [15:0] $end
$var reg 16 ) re_coeff [15:0] $end
$var integer 32 * i [31:0] $end
$var integer 32 + num_iterations [31:0] $end
$scope module uut $end
$var wire 16 , accu_im_init [15:0] $end
$var wire 16 - accu_re_init [15:0] $end
$var wire 1 % clk $end
$var wire 16 . im_coeff [15:0] $end
$var wire 1 ' load $end
$var wire 16 / power [15:0] $end
$var wire 16 0 re_coeff [15:0] $end
$var reg 32 1 ac3 [31:0] $end
$var reg 16 2 accu_im [15:0] $end
$var reg 16 3 accu_re [15:0] $end
$var reg 16 4 t0 [15:0] $end
$var reg 32 5 temp_im [31:0] $end
$var reg 32 6 temp_re [31:0] $end
$var reg 16 7 tmph_im [15:0] $end
$var reg 16 8 tmph_re [15:0] $end
$upscope $end
$upscope $end
$enddefinitions $end
#0
$dumpvars
bx 8
bx 7
bx 6
bx 5
bx 4
bx 3
bx 2
bx 1
b111110100110100 0
b10000000000 /
b1101010011101 .
b100000 -
b0 ,
b1111101000 +
bx *
b111110100110100 )
b10000000000 (
1'
b1101010011101 &
0%
b100000 $
b0 #
bx "
bx !
$end
#5000
b0 "
b0 2
b100000 !
b100000 3
1%
#10000
0%
b0 *
0'
#15000
b110 "
b110 2
b1111111111 4
b11111111111111110000011011 1
b110 7
b11111 8
b110110101110011010 5
b100000010001001100001 6
1%
#20000
0%
b1 *
#25000
b1100 "
b1100 2
b11110 !
b11110 3
b11111111111111101111101100 1
b1100 7
b11110 8
b1100111001011001100 5
b11110111111010110100 6
1%
#30000
0%
b10 *
#35000
b10010 "
b10010 2
b11011 !
b11011 3
b11111111111111110000111011 1
b10001 7
b11010 8
b10010100000011000101 5
b11011101010010100010 6
1%
#40000
0%
b11 *
#45000
b10111 "
b10111 2
b10111 !
b10111 3
b11111111111111110000001011 1
b10111 7
b10110 8
b10111111100000100000 5
b10111010110101011100 6
1%
#50000
0%
b100 *
#55000
b11100 "
b11100 2
b10010 !
b10010 3
b11111111111111110000000110 1
b11011 7
b10001 8
b11100000111110101100 5
b10010001111110000000 6
1%
#60000
0%
b101 *
#65000
b100000 "
b100000 2
b1100 !
b1100 3
b11111111111111101111000110 1
b11111 7
b1011 8
b100000000110010011011 5
b1100001000001110001 6
1%
#70000
0%
b110 *
#75000
b100010 "
b100010 2
b101 !
b101 3
b11111111111111101110100110 1
b100001 7
b101 8
b100010110100110111011 5
b101001111011001011 6
1%
#80000
0%
b111 *
#85000
b100011 "
b100011 2
b1111111111111101 !
b1111111111111101 3
b11111111111111101101110011 1
b100010 7
b1111111111111101 8
b100011010110111010111 5
b11111111111111101101110100101101 6
1%
#90000
0%
b1000 *
#95000
b100010 "
b100010 2
b1111111111110101 !
b1111111111110101 3
b11111111111111101101000110 1
b100001 7
b1111111111110101 8
b100010101001000100100 5
b11111111111110101011100011111000 6
1%
#100000
0%
b1001 *
#105000
b11111 "
b11111 2
b1111111111101101 !
b1111111111101101 3
b11111111111111101100111000 1
b11110 7
b1111111111101110 8
b11111111010000001011 5
b11111111111101101100110111111100 6
1%
#110000
0%
b1010 *
#115000
b11011 "
b11011 2
b1111111111100110 !
b1111111111100110 3
b11111111111111101010111000 1
b11010 7
b1111111111100110 8
b11011001011110001011 5
b11111111111100110001010000111011 6
1%
#120000
0%
b1011 *
#125000
b10101 "
b10101 2
b1111111111011111 !
b1111111111011111 3
b11111111111111101001000111 1
b10101 7
b1111111111100000 8
b10101101010001110101 5
b11111111111011111111101001001001 6
1%
#130000
0%
b1100 *
#135000
b1110 "
b1110 2
b1111111111011010 !
b1111111111011010 3
b11111111111111100111111110 1
b1101 7
b1111111111011011 8
b1110000101011111010 5
b11111111111011010001100110010000 6
1%
#140000
0%
b1101 *
#145000
b101 "
b101 2
b1111111111010110 !
b1111111111010110 3
b11111111111111100101010110 1
b101 7
b1111111111010111 8
b101111100110000101 5
b11111111111010110101000111011011 6
1%
#150000
0%
b1110 *
#155000
b1111111111111100 "
b1111111111111100 2
b1111111111010100 !
b1111111111010100 3
b11111111111111100010110111 1
b1111111111111100 7
b1111111111010101 8
b11111111111111100000010001000110 5
b11111111111010100100010010010010 6
1%
#160000
0%
b1111 *
#165000
b1111111111110010 "
b1111111111110010 2
b11111111111111100000000011 1
b1111111111110010 7
b11111111111110010100000001000010 5
b11111111111010100011100110101111 6
1%
#170000
0%
b10000 *
#175000
b1111111111101000 "
b1111111111101000 2
b1111111111010110 !
b1111111111010110 3
b11111111111111011101011110 1
b1111111111101001 7
b1111111111010111 8
b11111111111101000011100001000011 5
b11111111111010110100101111001111 6
1%
#180000
0%
b10001 *
#185000
b1111111111011110 "
b1111111111011110 2
b1111111111011010 !
b1111111111011010 3
b11111111111111011001100110 1
b1111111111011111 7
b1111111111011011 8
b11111111111011110110000101111111 5
b11111111111011010110000001010101 6
1%
#190000
0%
b10010 *
#195000
b1111111111010101 "
b1111111111010101 2
b1111111111100000 !
b1111111111100000 3
b11111111111111010101011011 1
b1111111111010110 7
b1111111111100001 8
b11111111111010101100001111110100 5
b11111111111100000111011101000001 6
1%
#200000
0%
b10011 *
#205000
b1111111111001101 "
b1111111111001101 2
b1111111111101000 !
b1111111111101000 3
b11111111111111010010001110 1
b1111111111001111 7
b1111111111101001 8
b11111111111001101110000011010101 5
b11111111111101000111010111110110 6
1%
#210000
0%
b10100 *
#215000
b1111111111000111 "
b1111111111000111 2
b1111111111110010 !
b1111111111110010 3
b11111111111111001110000110 1
b1111111111001001 7
b1111111111110011 8
b11111111111000111011010000100011 5
b11111111111110010101110001110100 6
1%
#220000
0%
b10101 *
#225000
b1111111111000011 "
b1111111111000011 2
b1111111111111110 !
b1111111111111110 3
b11111111111111001001100011 1
b1111111111000101 7
b1111111111111110 8
b11111111111000011011111100010001 5
b11111111111111110000110000011111 6
1%
#230000
0%
b10110 *
#235000
b1111111111000010 "
b1111111111000010 2
b1011 !
b1011 3
b11111111111111000100010011 1
b1111111111000011 7
b1010 8
b11111111111000010000000110011111 5
b1011000010011110111 6
1%
#240000
0%
b10111 *
#245000
b1111111111000011 "
b1111111111000011 2
b11000 !
b11000 3
b11111111111111000001010110 1
b1111111111000101 7
b10111 8
b11111111111000011110011001100010 5
b11000010111100101011 6
1%
#250000
0%
b11000 *
#255000
b1111111111000111 "
b1111111111000111 2
b100101 !
b100101 3
b11111111111110111100011111 1
b1111111111001001 7
b100100 8
b11111111111000111100110110001011 5
b100101010010000100101 6
1%
#260000
0%
b11001 *
#265000
b1111111111001110 "
b1111111111001110 2
b110001 !
b110001 3
b11111111111110110110011111 1
b1111111111001111 7
b110000 8
b11111111111001110011010001001110 5
b110001100010101001001 6
1%
#270000
0%
b11010 *
#275000
b1111111111011000 "
b1111111111011000 2
b111100 !
b111100 3
b11111111111110110011101011 1
b1111111111011001 7
b111010 8
b11111111111011000000100000001100 5
b111100001000101100100 6
1%
#280000
0%
b11011 *
#285000
b1111111111100100 "
b1111111111100100 2
b1000101 !
b1000101 3
b11111111111110101110011110 1
b1111111111100101 7
b1000011 8
b11111111111100100100000011000111 5
b1000101000110001110101 6
1%
#290000
0%
b11100 *
#295000
b1111111111110010 "
b1111111111110010 2
b1001011 !
b1001011 3
b11111111111110101001101011 1
b1111111111110010 7
b1001001 8
b11111111111110010100001010101111 5
b1001011100101111100111 6
1%
#300000
0%
b11101 *
#305000
b1 "
b1 2
b1001110 !
b1001110 3
b11111111111110100101101111 1
b1 7
b1001100 8
b1111011100100110 5
b1001110101001010000110 6
1%
#310000
0%
b11110 *
#315000
b10001 "
b10001 2
b11111111111110100001001111 1
b10001 7
b10001101110011111001 5
b1001110011101011101111 6
1%
#320000
0%
b11111 *
#325000
b100001 "
b100001 2
b1001011 !
b1001011 3
b11111111111110011111000000 1
b100000 7
b1001000 8
b100001110110000101010 5
b1001011000000100100011 6
1%
#330000
0%
b100000 *
#335000
b110001 "
b110001 2
b1000100 !
b1000100 3
b11111111111110011001011011 1
b101111 7
b1000010 8
b110001010101110000100 5
b1000100100011110111101 6
1%
#340000
0%
b100001 *
#345000
b1000000 "
b1000000 2
b111010 !
b111010 3
b11111111111110010010111100 1
b111110 7
b111000 8
b1000000000000001101010 5
b111010000100110001011 6
1%
#350000
0%
b100010 *
#355000
b1001100 "
b1001100 2
b101100 !
b101100 3
b11111111111110001101100011 1
b1001010 7
b101011 8
b1001100111110001001000 5
b101100110001001011101 6
1%
#360000
0%
b100011 *
#365000
b1010110 "
b1010110 2
b11100 !
b11100 3
b11111111111110001000111110 1
b1010011 7
b11011 8
b1010110000101000011001 5
b11100000101000111001 6
1%
#370000
0%
b100100 *
#375000
b1011100 "
b1011100 2
b1001 !
b1001 3
b11111111111110000010111110 1
b1011001 7
b1001 8
b1011100101110001001011 5
b1001110010011101001 6
1%
#380000
0%
b100101 *
#385000
b1011110 "
b1011110 2
b1111111111110101 !
b1111111111110101 3
b11111111111101111100101110 1
b1011011 7
b1111111111110101 8
b1011110101100111011010 5
b11111111111110101010101001110011 6
1%
#390000
0%
b100110 *
#395000
b1011100 "
b1011100 2
b1111111111100000 !
b1111111111100000 3
b11111111111101110101001110 1
b1011001 7
b1111111111100001 8
b1011100011100000000000 5
b11111111111100000101110100111101 6
1%
#400000
0%
b100111 *
#405000
b1010101 "
b1010101 2
b1111111111001011 !
b1111111111001011 3
b11111111111101101011101110 1
b1010011 7
b1111111111001101 8
b1010101111011010111101 5
b11111111111001011111110101000111 6
1%
#410000
0%
b101000 *
#415000
b1001010 "
b1001010 2
b1111111110111000 !
b1111111110111000 3
b11111111111101100010011100 1
b1001000 7
b1111111110111010 8
b1001010010111101111011 5
b11111111110111000010011001100001 6
1%
#420000
0%
b101001 *
#425000
b111011 "
b111011 2
b1111111110100111 !
b1111111110100111 3
b11111111111101011001101011 1
b111001 7
b1111111110101010 8
b111011001100010100111 5
b11111111110100111100000001010100 6
1%
#430000
0%
b101010 *
#435000
b101000 "
b101000 2
b1111111110011001 !
b1111111110011001 3
b11111111111101001011111111 1
b100111 7
b1111111110011100 8
b101000011011001000000 5
b11111111110011001100011100100001 6
1%
#440000
0%
b101011 *
#445000
b10010 "
b10010 2
b1111111110001111 !
b1111111110001111 3
b11111111111100111110011011 1
b10001 7
b1111111110010010 8
b10010001111011100100 5
b11111111110001111011111111111010 6
1%
#450000
0%
b101100 *
#455000
b1111111111111001 "
b1111111111111001 2
b1111111110001010 !
b1111111110001010 3
b11111111111100110000110011 1
b1111111111111010 7
b1111111110001101 8
b11111111111111001111011001100001 5
b11111111110001010001000101110101 6
1%
#460000
0%
b101101 *
#465000
b1111111111011111 "
b1111111111011111 2
b11111111111100100100111100 1
b1111111111100000 7
b1111111110001110 8
b11111111111011111100111101010110 5
b11111111110001010011110011000101 6
1%
#470000
0%
b101110 *
#475000
b1111111111000101 "
b1111111111000101 2
b1111111110010000 !
b1111111110010000 3
b11111111111100010011100110 1
b1111111111000111 7
b1111111110010011 8
b11111111111000101011010000100111 5
b11111111110010000000010010110010 6
1%
#480000
0%
b101111 *
#485000
b1111111110101100 "
b1111111110101100 2
b1111111110011011 !
b1111111110011011 3
b11111111111100000011011011 1
b1111111110101111 7
b1111111110011110 8
b11111111110101100011110010100101 5
b11111111110011011101001111010001 6
1%
#490000
0%
b110000 *
#495000
b1111111110010101 "
b1111111110010101 2
b1111111110101100 !
b1111111110101100 3
b11111111111011101101111100 1
b1111111110011000 7
b1111111110101110 8
b11111111110010101100101101100111 5
b11111111110101100000111001010010 6
1%
#500000
0%
b110001 *
#505000
b1111111110000010 "
b1111111110000010 2
b1111111111000010 !
b1111111111000010 3
b11111111111011011011010111 1
b1111111110000101 7
b1111111111000100 8
b11111111110000010000010000111011 5
b11111111111000010001101011001011 6
1%
#510000
0%
b110010 *
#515000
b1111111101110011 "
b1111111101110011 2
b1111111111011100 !
b1111111111011100 3
b11111111111011000111100110 1
b1111111101110111 7
b1111111111011101 8
b11111111101110011100101011101011 5
b11111111111011100011101011010001 6
1%
#520000
0%
b110011 *
#525000
b1111111101101010 "
b1111111101101010 2
b1111111111111001 !
b1111111111111001 3
b11111111111010110010011000 1
b1111111101101110 7
b1111111111111010 8
b11111111101101010000010011011010 5
b11111111111111001111010100101111 6
1%
#530000
0%
b110100 *
#535000
b1111111101100111 "
b1111111101100111 2
b11001 !
b11001 3
b11111111111010011100000111 1
b1111111101101011 7
b11000 8
b11111111101100111001010111010010 5
b11001000101101111010 6
1%
#540000
0%
b110101 *
#545000
b1111111101101011 "
b1111111101101011 2
b111010 !
b111010 3
b11111111111010000110011111 1
b1111111101101111 7
b111000 8
b11111111101101011000000111010010 5
b111010000000110110001 6
1%
#550000
0%
b110110 *
#555000
b1111111101110110 "
b1111111101110110 2
b1011010 !
b1011010 3
b11111111111001110001001011 1
b1111111101111010 7
b1010111 8
b11111111101110110001000011010100 5
b1011010011011011010010 6
1%
#560000
0%
b110111 *
#565000
b1111111110001000 "
b1111111110001000 2
b1111000 !
b1111000 3
b11111111111001010111110111 1
b1111111110001011 7
b1110100 8
b11111111110001000000100110011111 5
b1111000010110001110110 6
1%
#570000
0%
b111000 *
#575000
b1111111110100000 "
b1111111110100000 2
b10010010 !
b10010010 3
b11111111111000111101110011 1
b1111111110100011 7
b10001110 8
b11111111110100000101010110010101 5
b10010010110000101101010 6
1%
#580000
0%
b111001 *
#585000
b1111111110111110 "
b1111111110111110 2
b10100111 !
b10100111 3
b11111111111000100101111100 1
b1111111111000000 7
b10100010 8
b11111111110111110011101001001010 5
b10100111110100111100110 6
1%
#590000
0%
b111010 *
#595000
b1111111111100001 "
b1111111111100001 2
b10110110 !
b10110110 3
b11111111111000001000011011 1
b1111111111100010 7
b10110001 8
b11111111111100001001110100100001 5
b10110110100110010110101 6
1%
#600000
0%
b111011 *
#605000
b111 "
b111 2
b10111110 !
b10111110 3
b11111111110111101110001111 1
b111 7
b10111000 8
b111101111001001011 5
b10111110001101101000011 6
1%
#610000
0%
b111100 *
#615000
b101111 "
b101111 2
b11111111110111001101111100 1
b101110 7
b101111110010011000100 5
b10111110001000110010101 6
1%
#620000
0%
b111101 *
#625000
b1011000 "
b1011000 2
b10110101 !
b10110101 3
b11111111110110101011000111 1
b1010101 7
b10110000 8
b1011000001000010111101 5
b10110101100100100010101 6
1%
#630000
0%
b111110 *
#635000
b1111111 "
b1111111 2
b10100011 !
b10100011 3
b11111111110110001101100011 1
b1111011 7
b10011110 8
b1111111100011001100110 5
b10100011101011100101110 6
1%
#640000
0%
b111111 *
#645000
b10100011 "
b10100011 2
b10001001 !
b10001001 3
b11111111110101100101100011 1
b10011110 7
b10000101 8
b10100011000011000100101 5
b10001001001011110110100 6
1%
#650000
0%
b1000000 *
#655000
b11000001 "
b11000001 2
b1100111 !
b1100111 3
b11111111110101000001010111 1
b10111011 7
b1100100 8
b11000001110000101100110 5
b1100111001111001111001 6
1%
#660000
0%
b1000001 *
#665000
b11011000 "
b11011000 2
b111110 !
b111110 3
b11111111110100010110101100 1
b11010010 7
b111100 8
b11011000110000010001101 5
b111110011111101010011 6
1%
#670000
0%
b1000010 *
#675000
b11100111 "
b11100111 2
b10000 !
b10000 3
b11111111110011101100011111 1
b11100000 7
b1111 8
b11100111001010100000110 5
b10000001101000010001 6
1%
#680000
0%
b1000011 *
#685000
b11101100 "
b11101100 2
b1111111111011110 !
b1111111111011110 3
b11111111110010111011100110 1
b11100101 7
b1111111111011111 8
b11101100011011011010111 5
b11111111111011110100101110110110 6
1%
#690000
0%
b1000100 *
#695000
b11100110 "
b11100110 2
b1111111110101011 !
b1111111110101011 3
b11111111110010001011010110 1
b11011111 7
b1111111110101101 8
b11100110101111000110111 5
b11111111110101011000101010101111 6
1%
#700000
0%
b1000101 *
#705000
b11010101 "
b11010101 2
b1111111101111000 !
b1111111101111000 3
b11111111110001010110010110 1
b11001111 7
b1111111101111101 8
b11010101110000111001000 5
b11111111101111000111100100110001 6
1%
#710000
0%
b1000110 *
#715000
b10111001 "
b10111001 2
b1111111101001001 !
b1111111101001001 3
b11111111110000010110101100 1
b10110100 7
b1111111101001110 8
b10111001101100000101000 5
b11111111101001001001000001110001 6
1%
#720000
0%
b1000111 *
#725000
b10010011 "
b10010011 2
b1111111100011111 !
b1111111100011111 3
b1111111110 4
b11111111101111011110011000 1
b10001110 7
b1111111100100110 8
b10010011010101100111101 5
b11111111100011111101111000010011 6
1%
#730000
0%
b1001000 *
#735000
b1100100 "
b1100100 2
b1111111011111101 !
b1111111011111101 3
b11111111101110010100100110 1
b1100001 7
b1111111100000101 8
b1100100000010000011101 5
b11111111011111101100001100011011 6
1%
#740000
0%
b1001001 *
#745000
b101101 "
b101101 2
b1111111011100101 !
b1111111011100101 3
b11111111101101000101011110 1
b101011 7
b1111111011101101 8
b101101010011100100011 5
b11111111011100101010010100110110 6
1%
#750000
0%
b1001010 *
#755000
b1111111111110000 "
b1111111111110000 2
b1111111011011000 !
b1111111011011000 3
b11111111101011110101011110 1
b1111111111110001 7
b1111111011100001 8
b11111111111110000101101010110011 5
b11111111011011000111000000101001 6
1%
#760000
0%
b1001011 *
#765000
b1111111110110000 "
b1111111110110000 2
b11111111101010011001111011 1
b1111111110110010 7
b11111111110110000010111111010100 5
b11111111011011000110101111101110 6
1%
#770000
0%
b1001100 *
#775000
b1111111101101111 "
b1111111101101111 2
b1111111011100110 !
b1111111011100110 3
b11111111101001000001001111 1
b1111111101110100 7
b1111111011101111 8
b11111111101101111110101101010000 5
b11111111011100110100101100010010 6
1%
#780000
0%
b1001101 *
#785000
b1111111100110001 "
b1111111100110001 2
b1111111100000010 !
b1111111100000010 3
b11111111100111010111001011 1
b1111111100110111 7
b1111111100001010 8
b11111111100110001010001000101100 5
b11111111100000010101000110010001 6
1%
#790000
0%
b1001110 *
#795000
b1111111011111000 "
b1111111011111000 2
b1111111100101100 !
b1111111100101100 3
b11111111100101101000111100 1
b1111111100000000 7
b1111111100110010 8
b11111111011111000101110100101110 5
b11111111100101100001010011110111 6
1%
#800000
0%
b1001111 *
#805000
b1111111011001000 "
b1111111011001000 2
b1111111101100010 !
b1111111101100010 3
b11111111100011110111101110 1
b1111111011010001 7
b1111111101100111 8
b11111111011001000001111010111010 5
b11111111101100010110000000001010 6
1%
#810000
0%
b1010000 *
#815000
b1111111010100011 "
b1111111010100011 2
b1111111110100011 !
b1111111110100011 3
b11111111100001111101110011 1
b1111111010101101 7
b1111111110100110 8
b11111111010100011011001001100000 5
b11111111110100011100000111110100 6
1%
#820000
0%
b1010001 *
#825000
b1111111010001100 "
b1111111010001100 2
b1111111111101101 !
b1111111111101101 3
b11111111100000000110000110 1
b1111111010010111 7
b1111111111101101 8
b11111111010001100000001111100101 5
b11111111111101101000000001001011 6
1%
#830000
0%
b1010010 *
#835000
b1111111010000100 "
b1111111010000100 2
b111100 !
b111100 3
b1111111101 4
b11111111011110000111011100 1
b1111111010010000 7
b111010 8
b11111111010000100101101100011001 5
b111100100100010011010 6
1%
#840000
0%
b1010011 *
#845000
b1111111010001101 "
b1111111010001101 2
b10001101 !
b10001101 3
b11111111011011110001101111 1
b1111111010011000 7
b10001001 8
b11111111010001101100011111010100 5
b10001101111101110100001 6
1%
#850000
0%
b1010100 *
#855000
b1111111010101000 "
b1111111010101000 2
b11011101 !
b11011101 3
b11111111011001011110101011 1
b1111111010110010 7
b11010111 8
b11111111010101000000001000000111 5
b11011101110000010100110 6
1%
#860000
0%
b1010101 *
#865000
b1111111011010100 "
b1111111011010100 2
b100101000 !
b100101000 3
b11111111010111001101110110 1
b1111111011011101 7
b100011111 8
b11111111011010100011001100010010 5
b100101000101000101111111 6
1%
#870000
0%
b1010110 *
#875000
b1111111100010000 "
b1111111100010000 2
b101101010 !
b101101010 3
b11111111010100110001111111 1
b1111111100011000 7
b101011111 8
b11111111100010000110111101010000 5
b101101010110101111111111 6
1%
#880000
0%
b1010111 *
#885000
b1111111101011011 "
b1111111101011011 2
b110100000 !
b110100000 3
b11111111010010000110010111 1
b1111111101100000 7
b110010011 8
b11111111101011011100001100100010 5
b110100000100010111111111 6
1%
#890000
0%
b1011000 *
#895000
b1111111110110010 "
b1111111110110010 2
b111000110 !
b111000110 3
b1111111100 4
b11111111001111001001010110 1
b1111111110110101 7
b110111001 8
b11111111110110010110000111001000 5
b111000110111100011001101 6
1%
#900000
0%
b1011001 *
#905000
b10010 "
b10010 2
b111011010 !
b111011010 3
b11111111001100010000101100 1
b10010 7
b111001100 8
b10010101010001001110 5
b111011010100111011011110 6
1%
#910000
0%
b1011010 *
#915000
b1110111 "
b1110111 2
b11111111001001010001110111 1
b1110100 7
b111001011 8
b1110111110001010001010 5
b111011010001100000010010 6
1%
#920000
0%
b1011011 *
#925000
b11011101 "
b11011101 2
b111000100 !
b111000100 3
b11111111000101111110111000 1
b11010110 7
b110110110 8
b11011101100111010000110 5
b111000100100010001110101 6
1%
#930000
0%
b1011100 *
#935000
b100111111 "
b100111111 2
b110011000 !
b110011000 3
b11111111000010010000001100 1
b100110110 7
b110001100 8
b100111111110011001000000 5
b110011000100000000010111 6
1%
#940000
0%
b1011101 *
#945000
b110011001 "
b110011001 2
b101010111 !
b101010111 3
b1111111011 4
b11111110111110110011100000 1
b110001100 7
b101001100 8
b110011001001011001001000 5
b101010111000101011000001 6
1%
#950000
0%
b1011110 *
#955000
b111100110 "
b111100110 2
b100000010 !
b100000010 3
b11111110111010100101001011 1
b111010111 7
b11111010 8
b111100110000001100111100 5
b100000010001111011110101 6
1%
#960000
0%
b1011111 *
#965000
b1000100001 "
b1000100001 2
b10011100 !
b10011100 3
b11111110110110000111001110 1
b1000010001 7
b10010111 8
b1000100001011110010011101 5
b10011100000000101100111 6
1%
#970000
0%
b1100000 *
#975000
b1001000111 "
b1001000111 2
b101000 !
b101000 3
b11111110110001101100010110 1
b1000110101 7
b100111 8
b1001000111000110001010111 5
b101000011111010110000 6
1%
#980000
0%
b1100001 *
#985000
b1001010100 "
b1001010100 2
b1111111110101011 !
b1111111110101011 3
b1111111010 4
b11111110101100110000010011 1
b1001000010 7
b1111111110101101 8
b1001010100100010001101000 5
b11111111110101011010101010000111 6
1%
#990000
0%
b1100010 *
#995000
b1001000110 "
b1001000110 2
b1111111100101010 !
b1111111100101010 3
b11111110100111100000000111 1
b1000110101 7
b1111111100110000 8
b1001000110110110110110001 5
b11111111100101010011110100011000 6
1%
#1000000
0%
b1100011 *
#1005000
b1000011101 "
b1000011101 2
b1111111010101011 !
b1111111010101011 3
b11111110100010001101110111 1
b1000001100 7
b1111111010110101 8
b1000011101000100010110010 5
b11111111010101011011000101011100 6
1%
#1010000
0%
b1100100 *
#1015000
b111011000 "
b111011000 2
b1111111000110100 !
b1111111000110100 3
b1111111001 4
b11111110011100000000011011 1
b111001010 7
b1111111001000001 8
b111011000011111100111101 5
b11111111000110100000110000101100 6
1%
#1020000
0%
b1100101 *
#1025000
b101111001 "
b101111001 2
b1111110111001010 !
b1111110111001010 3
b11111110010101101101100011 1
b101101110 7
b1111110111011011 8
b101111001011001111000010 5
b11111110111001010111000000011011 6
1%
#1030000
0%
b1100110 *
#1035000
b100000010 "
b100000010 2
b1111110101110100 !
b1111110101110100 3
b1111111000 4
b11111110001110110010110110 1
b11111011 7
b1111110110000111 8
b100000010110111010011110 5
b11111110101110100010110110011011 6
1%
#1040000
0%
b1100111 *
#1045000
b1111000 "
b1111000 2
b1111110100110111 !
b1111110100110111 3
b11111110000111110011100000 1
b1110100 7
b1111110101001100 8
b1111000011001011101100 5
b11111110100110111001001011110110 6
1%
#1050000
0%
b1101000 *
#1055000
b1111111111100000 "
b1111111111100000 2
b1111110100010111 !
b1111110100010111 3
b11111110000000001001010110 1
b1111111111100001 7
b1111110100101101 8
b11111111111100000001011000010011 5
b11111110100010111001101100101100 6
1%
#1060000
0%
b1101001 *
#1065000
b1111111101000000 "
b1111111101000000 2
b1111110111 4
b11111101110111110101111110 1
b1111111101000101 7
b11111111101000000000000100101110 5
b11111110100010111100010010110111 6
1%
#1070000
0%
b1101010 *
#1075000
b1111111010011110 "
b1111111010011110 2
b1111110100111001 !
b1111110100111001 3
b1111110110 4
b11111101101111011000001110 1
b1111111010101001 7
b1111110101001111 8
b11111111010011110101011110000001 5
b11111110100111001111000001010110 6
1%
#1080000
0%
b1101011 *
#1085000
b1111111000000010 "
b1111111000000010 2
b1111110101111110 !
b1111110101111110 3
b11111101100101101110011011 1
b1111111000010001 7
b1111110110010010 8
b11111111000000010100101101100011 5
b11111110101111110111000111111010 6
1%
#1090000
0%
b1101100 *
#1095000
b1111110101110100 "
b1111110101110100 2
b1111110111100101 !
b1111110111100101 3
b1111110101 4
b11111101011011101001101011 1
b1111110110000111 7
b1111110111110110 8
b11111110101110100000101111100001 5
b11111110111100101111011011001100 6
1%
#1100000
0%
b1101101 *
#1105000
b1111110011111010 "
b1111110011111010 2
b1111111001101100 !
b1111111001101100 3
b11111101010001001001111100 1
b1111110100010010 7
b1111111001111000 8
b11111110011111010111111100111011 5
b11111111001101100001110000111000 6
1%
#1110000
0%
b1101110 *
#1115000
b1111110010011100 "
b1111110010011100 2
b1111111100001110 !
b1111111100001110 3
b1111110100 4
b11111101000101011011100011 1
b1111110010110110 7
b1111111100010101 8
b11111110010011100111010001111100 5
b11111111100001110011111110100010 6
1%
#1120000
0%
b1101111 *
#1125000
b1111110001100000 "
b1111110001100000 2
b1111111111000110 !
b1111111111000110 3
b1111110011 4
b11111100111001011100111111 1
b1111110001111100 7
b1111111111000111 8
b11111110001100000111000011111010 5
b11111111111000110000000000010001 6
1%
#1130000
0%
b1110000 *
#1135000
b1111110001001011 "
b1111110001001011 2
b10001100 !
b10001100 3
b1111110010 4
b11111100101100110110000000 1
b1111110001101000 7
b10001000 8
b11111110001001011110111000111110 5
b10001100011001111101000 6
1%
#1140000
0%
b1110001 *
#1145000
b1111110001100001 "
b1111110001100001 2
b101011000 !
b101011000 3
b1111110001 4
b11111100011111000000101100 1
b1111110001111100 7
b101001110 8
b11111110001100001001000011010100 5
b101011000100010011011111 6
1%
#1150000
0%
b1110010 *
#1155000
b1111110010100011 "
b1111110010100011 2
b1000100001 !
b1000100001 3
b11111100010001000011001111 1
b1111110010111100 7
b1000010001 8
b11111110010100011000010010101000 5
b1000100001100000101100100 6
1%
#1160000
0%
b1110011 *
